tureng_cli/__init__.py
tureng_cli/get_tureng.py
tureng_cli/tureng.py
tureng_cli-0.1.2.dist-info/LICENCE.txt
tureng_cli-0.1.2.dist-info/METADATA
tureng_cli-0.1.2.dist-info/WHEEL
tureng_cli-0.1.2.dist-info/entry_points.txt
tureng_cli-0.1.2.dist-info/top_level.txt
tureng_cli-0.1.2.dist-info/RECORD
