Metadata-Version: 2.1
Name: tureng-cli
Version: 0.1.2
Summary: Tureng CLI
Home-page: https://github.com/hamitaksln/tureng-cli
Author: Abdulhamit Akaslan
Author-email: hamtaksln@gmail.com
License: MIT
Keywords: tureng
Platform: UNKNOWN
Classifier: Development Status :: 5 - Production/Stable
Classifier: Intended Audience :: Education
Classifier: Operating System :: Microsoft :: Windows :: Windows 10
Classifier: License :: OSI Approved :: MIT License
Classifier: Programming Language :: Python :: 3
Requires-Dist: requests
Requires-Dist: selectolax
Requires-Dist: docopt
